flask_kafka_publisher/__init__.py
flask_kafka_publisher-0.0.1.dist-info/METADATA
flask_kafka_publisher-0.0.1.dist-info/WHEEL
flask_kafka_publisher-0.0.1.dist-info/licenses/LICENSE
flask_kafka_publisher-0.0.1.dist-info/RECORD
