Metadata-Version: 2.1
Name: flask-kafka-publisher
Version: 0.0.1
Summary:  A Flask extension that simplifies publishing messages to Kafka within your Flask application.
Project-URL: Homepage, https://github.com/nobbbbby/flask-kafka-publisher
Project-URL: Bug Tracker, https://github.com/nobbbbby/flask-kafka-publisher/issues
Author-email: Nobby Tang <cnadytzar@gmail.com>
License-File: LICENSE
Classifier: License :: OSI Approved :: MIT License
Classifier: Operating System :: OS Independent
Classifier: Programming Language :: Python :: 3
Requires-Python: >=3.7
Requires-Dist: flask
Requires-Dist: kafka
